taopypy/modules/notification.py
taopypy/modules/x.py
taopypy/modules/formatter/error_formatter.py
taopypy/modules/handler/handler.py
taopypy-0.1.8.dist-info/LICENSE
taopypy-0.1.8.dist-info/METADATA
taopypy-0.1.8.dist-info/WHEEL
taopypy-0.1.8.dist-info/entry_points.txt
taopypy-0.1.8.dist-info/top_level.txt
taopypy-0.1.8.dist-info/RECORD
